packageTest/__init__.py
packageTest/packageTest.py
pychedule-0.0.6.data/scripts/test.py
test/__init__.py
test/test.py
pychedule-0.0.6.dist-info/METADATA
pychedule-0.0.6.dist-info/WHEEL
pychedule-0.0.6.dist-info/top_level.txt
pychedule-0.0.6.dist-info/RECORD
